kmeans/__init__.py
kmeans/animate.py
kmeans/base_funcs.py
kmeans/clustering.py
kmeans/segmentation.py
kmeans_tjdwill-1.0.4.dist-info/METADATA
kmeans_tjdwill-1.0.4.dist-info/WHEEL
kmeans_tjdwill-1.0.4.dist-info/licenses/LICENSE
kmeans_tjdwill-1.0.4.dist-info/RECORD
