Metadata-Version: 2.3
Name: kmeans-tjdwill
Version: 1.0.4
Summary: A function-based implementation of k-means clustering that maintains data association.
Project-URL: Homepage, https://github.com/tjdwill/kmeans
Project-URL: Docs, https://tjdwill.github.io/kmeans
Project-URL: Issues, https://github.com/tjdwill/kmeans/issues
Author-email: Terrance Williams <tjdwill.gh@gmail.com>
License: MIT License
License-File: LICENSE
Keywords: clustering,computer vision,data analysis,data processing,k-means,linear algebra,robotics
Classifier: License :: OSI Approved :: MIT License
Classifier: Operating System :: OS Independent
Classifier: Programming Language :: Python :: 3
Classifier: Programming Language :: Python :: 3.9
Classifier: Programming Language :: Python :: 3.10
Classifier: Programming Language :: Python :: 3.11
Classifier: Programming Language :: Python :: 3.12
Requires-Python: >=3.9
Requires-Dist: matplotlib
Requires-Dist: numpy
